gprmc/__init__.py
gprmc/convert.py
gprmc/time_convert.py
gprmc-0.0.6.dist-info/LICENSE.txt
gprmc-0.0.6.dist-info/METADATA
gprmc-0.0.6.dist-info/WHEEL
gprmc-0.0.6.dist-info/top_level.txt
gprmc-0.0.6.dist-info/RECORD
