Metadata-Version: 2.1
Name: gprmc
Version: 0.0.6
Summary: convert gprmc data
Home-page: https://gitlab.com/ak080495/gprmc
Author: arunkumar
Author-email: ak080495@gmail.com
Project-URL: Bug Tracker, https://gitlab.com/ak080495/gprmc/-/issues
Classifier: Programming Language :: Python :: 3
Classifier: License :: OSI Approved :: MIT License
Classifier: Operating System :: OS Independent
Requires-Python: >=3.6
License-File: LICENSE.txt
